MANIFEST.in
README.rst
setup.py
catalog/__init__.py
catalog/admin.py
catalog/apps.py
catalog/cart_modifiers.py
catalog/cms_app.py
catalog/fields.py
catalog/filters.py
catalog/forms.py
catalog/managers.py
catalog/models.py
catalog/modifier_conditions.py
catalog/settings.py
catalog/shop_urls.py
catalog/urls.py
catalog/views.py
catalog/widgets.py
catalog/addresses/__init__.py
catalog/addresses/admin.py
catalog/addresses/models.py
catalog/addresses/management/__init__.py
catalog/addresses/management/commands/__init__.py
catalog/addresses/management/commands/initcountries.py
catalog/locale/hr/LC_MESSAGES/django.mo
catalog/locale/hr/LC_MESSAGES/django.po
catalog/migrations/0001_initial.py
catalog/migrations/0002_auto__del_field_cartmodifiercode_can_be_deleted__add_field_cartmodifie.py
catalog/migrations/0003_auto__del_field_modifiercode_num_uses__del_field_modifiercode_max_uses.py
catalog/migrations/0004_auto__add_productflag__add_unique_productflag_product_flag__add_flag__.py
catalog/migrations/0005_auto__chg_field_flag_code.py
catalog/migrations/0006_auto__add_field_category_featured_image__add_field_category_body__add_.py
catalog/migrations/0007_auto__add_field_brandtranslation_description__add_field_categorytransl.py
catalog/migrations/0008_auto__add_field_manufacturertranslation_description.py
catalog/migrations/0009_auto__add_relatedproduct.py
catalog/migrations/0010_auto__del_field_relatedproduct_bidirectional__chg_field_relatedproduct.py
catalog/migrations/__init__.py
catalog/orders/__init__.py
catalog/orders/admin.py
catalog/orders/models.py
catalog/orders/notifications.py
catalog/orders/urls.py
catalog/reviews/__init__.py
catalog/reviews/admin.py
catalog/reviews/models.py
catalog/reviews/urls.py
catalog/reviews/views.py
catalog/templates/admin/catalog/product_change_form.html
catalog/templatetags/__init__.py
catalog/templatetags/catalog_tags.py
catalog/templatetags/catalog_utils_tags.py
catalog/utils/__init__.py
catalog/utils/noconflict.py
django_shop_catalog.egg-info/PKG-INFO
django_shop_catalog.egg-info/SOURCES.txt
django_shop_catalog.egg-info/dependency_links.txt
django_shop_catalog.egg-info/not-zip-safe
django_shop_catalog.egg-info/requires.txt
django_shop_catalog.egg-info/top_level.txt
