Metadata-Version: 1.1
Name: django-shop-catalog
Version: 0.0.3
Summary: Catalog app for django SHOP
Home-page: http://pypi.python.org/pypi/django-shop-catalog/
Author: Dino Perovic
Author-email: dino.perovic@gmail.com
License: BSD
Platform: UNKNOWN
Classifier: Development Status :: 3 - Alpha
Classifier: Environment :: Web Environment
Classifier: Framework :: Django
Classifier: Intended Audience :: Developers
Classifier: Operating System :: OS Independent
Classifier: Programming Language :: Python
Classifier: Topic :: Internet :: WWW/HTTP
